[
  {
    "name": "function",
    "pattern": ".*discussion.*"
  },
  {
    "name": "function",
    "pattern": ".*error message.*"
  },
  {
    "name": "function",
    "pattern": ".*guiding qa.*"
  },
  {
    "name": "function",
    "pattern": "\\bdiscussion\\b"
  },
  {
    "name": "function",
    "pattern": "\\berror message\\b"
  },
  {
    "name": "function",
    "pattern": "\\bguiding qa\\b"
  },
  {
    "name": "keywords",
    "pattern": "keywords .*"
  },
  {
    "name": "question_or_error_message",
    "pattern": "question_or_error_message .*"
  },
  {
    "name": "os",
    "pattern": "(mac\\ os\\ system|windows\\ system|linux\\ system)"
  },
  {
    "name": "pl",
    "pattern": "(python\\ programming\\ language|java\\ programming\\ language|c\\ programming\\ language)"
  }
]